LICENSE
MANIFEST.in
README.rst
setup.py
wet_copy.py
wet_copy.egg-info/PKG-INFO
wet_copy.egg-info/SOURCES.txt
wet_copy.egg-info/dependency_links.txt
wet_copy.egg-info/entry_points.txt
wet_copy.egg-info/requires.txt
wet_copy.egg-info/top_level.txt