Metadata-Version: 1.1
Name: wet-copy
Version: 1.3.1
Summary: Format and print wetlab protocols stored as text files in git repositories.
Home-page: https://github.com/kalekundert/wet_copy
Author: Kale Kundert
Author-email: kale.kundert@ucsf.edu
License: GPLv3
Download-URL: https://github.com/kalekundert/wet_copy/tarball/v1.3.1
Keywords: print,scientific,protocols
Platform: UNKNOWN
